<?xml version="1.0" encoding="UTF-8"?>

<!-- generated on Wed Apr 28 19:55:52 2021 by Eclipse SUMO GUI Version v1_7_0+1279-3ddeb2fc1c
<configuration xmlns:xsi="http://www.w3.org/2001/XMLSchema-instance" xsi:noNamespaceSchemaLocation="http://sumo.dlr.de/xsd/sumoConfiguration.xsd">

    <input>
        <net-file value="demo.net.xml"/>
        <route-files value="demo.rou.xml"/>
        <additional-files value="demo.add.xml"/>
    </input>

    <output>
        <tripinfo-output value="tripinfo.xml"/>
    </output>

    <traci_server>
        <remote-port value="60549"/>
    </traci_server>

</configuration>
-->

<detector xmlns:xsi="http://www.w3.org/2001/XMLSchema-instance" xsi:noNamespaceSchemaLocation="http://sumo.dlr.de/xsd/det_e1_file.xsd">
    <interval begin="0.00" end="141.00" id="det_0" nVehContrib="9" flow="229.79" occupancy="4.74" speed="7.40" harmonicMeanSpeed="7.12" length="5.22" nVehEntered="9"/>
</detector>
